edx_rest_api_client/__init__.py
edx_rest_api_client/__version__.py
edx_rest_api_client/auth.py
edx_rest_api_client/client.py
edx_rest_api_client/exceptions.py
edx_rest_api_client-6.2.0.dist-info/LICENSE
edx_rest_api_client-6.2.0.dist-info/METADATA
edx_rest_api_client-6.2.0.dist-info/WHEEL
edx_rest_api_client-6.2.0.dist-info/top_level.txt
edx_rest_api_client-6.2.0.dist-info/RECORD
