Metadata-Version: 2.2
Name: edx-rest-api-client
Version: 6.2.0
Summary: Client utilities to access various Open edX Platform REST APIs.
Home-page: https://github.com/openedx/edx-rest-api-client
Author: edX
Author-email: oscm@edx.org
License: Apache
Keywords: edx rest api client
Classifier: Development Status :: 5 - Production/Stable
Classifier: License :: OSI Approved :: Apache Software License
Classifier: Programming Language :: Python
Classifier: Programming Language :: Python :: 3.11
Classifier: Programming Language :: Python :: 3.12
Classifier: Framework :: Django
Classifier: Framework :: Django :: 4.2
Classifier: Framework :: Django :: 5.2
Classifier: Topic :: Internet
Classifier: Intended Audience :: Developers
Classifier: Environment :: Web Environment
License-File: LICENSE
Requires-Dist: PyJWT
Requires-Dist: edx-django-utils
Requires-Dist: requests
Dynamic: author
Dynamic: author-email
Dynamic: classifier
Dynamic: description
Dynamic: description-content-type
Dynamic: home-page
Dynamic: keywords
Dynamic: license
Dynamic: requires-dist
Dynamic: summary
